aston/__init__.py
aston/cache.py
aston/calibrations/__init__.py
aston/calibrations/isotopes.py
aston/peak/__init__.py
aston/peak/integrators.py
aston/peak/peak.py
aston/peak/peak_finding.py
aston/peak/peak_fitting.py
aston/peak/peak_models.py
aston/peak/peak_readers.py
aston/spectra/__init__.py
aston/spectra/analysis.py
aston/spectra/isotopes.py
aston/spectra/math.py
aston/spectra/spectrafile.py
aston/trace/__init__.py
aston/trace/baseline.py
aston/trace/events.py
aston/trace/math_chromatograms.py
aston/trace/math_traces.py
aston/trace/new_integrator.py
aston/trace/parser.py
aston/trace/trace.py
aston/tracefile/__init__.py
aston/tracefile/agilent_extra_cs.py
aston/tracefile/agilent_extra_mh.py
aston/tracefile/agilent_fid.py
aston/tracefile/agilent_ms.py
aston/tracefile/agilent_uv.py
aston/tracefile/bruker.py
aston/tracefile/inficon.py
aston/tracefile/mime.py
aston/tracefile/mzml.py
aston/tracefile/netcdf.py
aston/tracefile/other_files.py
aston/tracefile/thermo.py
aston/tracefile/waters.py
Aston-0.7.1.dist-info/LICENSE.txt
Aston-0.7.1.dist-info/METADATA
Aston-0.7.1.dist-info/WHEEL
Aston-0.7.1.dist-info/top_level.txt
Aston-0.7.1.dist-info/RECORD
