Metadata-Version: 2.1
Name: Aston
Version: 0.7.1
Summary: Mass/UV Spectral Analysis Program
Home-page: https://github.com/bovee/aston
Author: Roderick Bovee
Author-email: rbovee@gmail.com
License: BSD 3-Clause
Platform: Any
Classifier: Development Status :: 4 - Beta
Classifier: Intended Audience :: Science/Research
Classifier: License :: OSI Approved :: BSD License
Classifier: Operating System :: OS Independent
Classifier: Topic :: Scientific/Engineering :: Chemistry
Requires-Dist: numpy (>=1.16.4)
Requires-Dist: scipy (>=1.2.0)
Provides-Extra: plot
Requires-Dist: matplotlib ; extra == 'plot'
Requires-Dist: jupyter ; extra == 'plot'
